deptest.py
deptest/__init__.py
deptest/asserts.py
deptest/config_object.py
deptest/core.py
deptest/loader.py
deptest/log.py
deptest/tools.py
deptest/utils.py
deptest-0.2.1.dist-info/DESCRIPTION.rst
deptest-0.2.1.dist-info/METADATA
deptest-0.2.1.dist-info/RECORD
deptest-0.2.1.dist-info/WHEEL
deptest-0.2.1.dist-info/entry_points.txt
deptest-0.2.1.dist-info/metadata.json
deptest-0.2.1.dist-info/top_level.txt
