Metadata-Version: 2.0
Name: deptest
Version: 0.2.1
Summary: dependent testing framework
Home-page: https://github.com/reorx/deptest
Author: reorx
Author-email: novoreorx@gmail.com
License: UNKNOWN
Platform: UNKNOWN
